depcheck/__init__.py
depcheck/depchecker.py
depcheck/models.py
depcheck/readers.py
depcheck/util.py
depcheck/util_test.py
depcheck-0.3.2.dist-info/LICENSE.md
depcheck-0.3.2.dist-info/METADATA
depcheck-0.3.2.dist-info/WHEEL
depcheck-0.3.2.dist-info/entry_points.txt
depcheck-0.3.2.dist-info/RECORD
