Metadata-Version: 2.1
Name: depcheck
Version: 0.3.2
Summary: Python code quality package that helps in defining and restricting how components of your code may interact
Home-page: https://github.com/flix-tech/depcheck
License: MIT
Keywords: dependencies,hexagonal,architecture,jdepend,deptrac
Author: FlixMobility Tech
Author-email: open-source@flixbus.com
Requires-Python: >=3.9,<4.0
Classifier: License :: OSI Approved :: MIT License
Classifier: Programming Language :: Python :: 3
Classifier: Programming Language :: Python :: 3.9
Classifier: Programming Language :: Python :: 3.10
Classifier: Programming Language :: Python :: 3.11
Requires-Dist: PyYAML (>=6.0,<7.0)
Requires-Dist: pydeps (>=1.12.0,<2.0.0)
Project-URL: Documentation, https://github.com/flix-tech/depcheck
Project-URL: Repository, https://github.com/flix-tech/depcheck
